<?xml version="1.0" encoding="UTF-8"?>
<document id="00107347">
2009-10-02: <phrase id="327199">Irlandia</phrase>: powtórkowe referendum ws. <phrase id="490593">traktatu <phrase id="327200">lizbońskiego</phrase></phrase> 

Dzisiaj druga próba ratyfikacji traktatu <phrase id="327201">lizbońskiego</phrase>. O godzinie 8 rano <phrase id="327202">polskiego</phrase> czasu rozpoczęło się referendum dotyczące tego dokumentu. W czerwcu 2008 roku Irlandczycy powiedzieli zdecydowane „Nie”. W <phrase id="327204">Irlandii</phrase>, w przeciwieństwie do innych krajów <phrase id="327205">UE</phrase>, <phrase id="327206">unijny</phrase> traktat musi zdobyć aprobatę społeczeństwa. Do godziny 22 głosować ma prawo ponad trzy miliony obywateli. Wyniki będą znane jutro, ale sondaże przedwyborcze mówiły o 55 procentach przewagi zwolenników Traktatu. Jeśli wynik referendum będzie pozytywny, wejście w życie nowego dokumentu, będzie zależało jedynie od prezydentów <phrase id="327207">Czech</phrase> i <phrase id="327208">Polski</phrase> (parlamenty tych krajów już zatwierdziły Traktat). Dokument ten umocnić Unię, zwiększyć władzę <phrase id="327209">Parlamentu Europejskiego</phrase>, uprościć głosowania oraz wyznaczyć prezydenta i szefa dyplomacji <phrase id="327211">UE</phrase>. 

Dowiedz się więcej o traktacie lizbońskim w <phrase id="327213">Wikipedii</phrase> 
</document>