<?xml version="1.0" encoding="UTF-8"?>
<document id="00102768">
<phrase id="466624">Dziennik Urzędowy Ministra Finansów</phrase> z 31 maja 2006 Nr 5 poz. 43 

ZARZĄDZENIE Nr 11 MINISTRA FINANSÓW z dnia 25 maja 2006 r. zmieniające zarządzenie w sprawie nadania statutów izbom celnym i urzędom celnym 

Na podstawie art. 1 d ust. 4 ustawy z dnia 24 lipca 1999 r. o <phrase id="466625">Służbie Celnej</phrase> (Dz. U. z 2004 r. Nr 156, poz. 1641 i Nr 273, poz. 2703 oraz z 2005 r. Nr 167, poz. 1399) zarządza się, co następuje: 

§ 1 

W zarządzeniu nr 8 <phrase id="466626">Ministra Finansów</phrase> z dnia 22 kwietnia 2004 r. w sprawie nadania statutów <phrase id="466627">izbom celnym</phrase> i <phrase id="466628">urzędom celnym</phrase> (Dz. Urz. Min. Fin. Nr 4, poz. 21, Nr 19, poz. 237 i Nr 20, poz. 248 oraz z 2005 r. Nr 8, poz. 79, Nr 9 poz. 90 i Nr 12, poz. 119), wprowadza się następujące zmiany: 

1) w § 4: 

a) w ust. 1 dodaje się pkt 9 w brzmieniu: 

" 9) wydawania pozwoleń na stosowanie jako zgłoszenia tranzytowego manifestu lotniczego (procedura uproszczona - poziom 1), przesyłanego z wykorzystaniem systemu wymiany danych (procedura uproszczona - poziom 2) oraz prowadzenia procedury konsultacyjnej;", 

b) dodaje się ust. 11 w brzmieniu: 

" 11. W skład <phrase id="466629">Izby Celnej w Toruniu</phrase> wchodzi komórka sprawująca kontrolę prawidłowości przewozów towarowych transportem kolejowym realizująca zadania polegające w szczególności na: 

1) wzywaniu głównego zobowiązanego do uiszczania w urzędzie przeznaczenia należności celnych i podatków oraz należnych opłat - w przypadku stwierdzenia nieprawidłowości związanych z przewozem towarów; 

2) przesyłaniu do urzędu przeznaczenia dokumentów dotyczących przewozu towarów transportem kolejowym, w celu wszczęcia postępowania celnego."; 
</document>