<?xml version="1.0" encoding="UTF-8"?>
<document id="00101483">
<phrase id="427831">Herb gminy <phrase id="308291">Lututów</phrase></phrase> 

Herb <phrase id="58189">Lututowa</phrase> to herb miejscowości i gminy <phrase id="308292">Lututów</phrase> w <phrase id="427832">powiecie <phrase id="58191">wieruszowskim</phrase></phrase> w <phrase id="427833">województwie <phrase id="58192">łódzkim</phrase></phrase>. 

Herb ten przedstawia niebieską tarczę herbową, na której znajduje się biały (lub srebrny) kozioł zwrócony głową w prawo, z żółtymi (lub złotymi) rogami. Kozioł jest symbolem <phrase id="58193">Lututowa</phrase> od przynajmniej 600 lat. Najstarszą rzeczą, w której występuje on jako symbol miasta, to pieczęć Lututowa z roku 1532 (obecnie znajdująca się w zbiorach <phrase id="427835"><phrase id="58195">Muzeum Narodowego</phrase> w <phrase id="58196">Krakowie</phrase></phrase>), na której znajdują się litery LVTOLTOV, a pod nimi wizerunek kozła zwróconego w lewo. 
</document>