<?xml version="1.0" encoding="UTF-8"?>
<document id="00103748">
<phrase id="303560">MBP</phrase>: <phrase id="469577"><phrase id="311257">WIELKANOCNE</phrase> EKSPRESJE</phrase> 

W dniach 23 marca - 3 kwietnia 2009 r w <phrase id="469574"><phrase id="348974">Miejskiej Bibliotece Publicznej</phrase> w <phrase id="302951">Ozorkowie</phrase></phrase> swoje prace wystawią uczestnicy <phrase id="469575">Warsztatów Terapii Zajęciowej</phrase>, działających przy <phrase id="469576"><phrase id="303249"><phrase id="311256">Polskim</phrase> Stowarzyszeniu Ludzi Cierpiących na Padaczkę</phrase> w <phrase id="302952">Ozorkowie</phrase></phrase>. Na wystawie znajdą się obrazy, tradycyjne koszyczki wielkanocne i karty świąteczne. Wystawie prac plastycznych towarzyszyć będzie wystawa książek. 

Ekspozycję można oglądać w godzinach otwarcia biblioteki. Zapraszamy! 
</document>