<?xml version="1.0" encoding="UTF-8"?>
<document id="00102481">
<phrase id="288743">TOWARZYSTWO PRZYJACIÓŁ <phrase id="288746">OZORKOWA</phrase></phrase> zaprasza na <phrase id="288744">VI HISTORYCZNY SPACER PO <phrase id="288745">OZORKOWIE</phrase></phrase>. Celem spaceru jest zwiedzanie terenu byłych <phrase id="469316"><phrase id="288740">Zakładów Przemysłu Bawełnianego „MORFEO</phrase>”.</phrase> Zbiórka przed <phrase id="469317">Miejską Biblioteką Publiczną</phrase> przy ul. <phrase id="303338">Listopadowej</phrase> 6. 
</document>