<?xml version="1.0" encoding="UTF-8"?>
<document id="00100502">
<phrase id="31868">Smardy Dolne</phrase> 

Smardy Dolne – wieś w <phrase id="31870">Polsce</phrase> położona w <phrase id="343898">województwie <phrase id="52969">opolskim</phrase></phrase>, w <phrase id="343899">powiecie <phrase id="52971">kluczborskim</phrase></phrase>, w <phrase id="343900">gminie <phrase id="308312">Kluczbork</phrase></phrase>. 

W latach 1945-54 siedziba gminy <phrase id="308314">Smardy Dolne</phrase>. W latach 1975-1998 miejscowość administracyjnie należała do ówczesnego województwa <phrase id="52970">opolskiego</phrase>. 

W południowo-zachodniej części miejscowości znajduje się zespół pałacowo - parkowy o powierzchni 5 ha. W obecnym kształcie <phrase id="343902">pałac w Smardach</phrase> powstał w II połowie XIX wieku na podstawie projektu <phrase id="31877"><phrase id="32776">Carla</phrase> <phrase id="32777">Gotharda</phrase> Langhansa</phrase>, projektanta <phrase id="31880">Bramy Brandenburskiej</phrase> w <phrase id="31881">Berlinie</phrase>. Obecnie pałac stanowi własność prywatną. 
</document>